common/__init__.py
common/compat/__init__.py
common/config/__init__.py
common/utils/__init__.py
libequalizer-1.0.0.dist-info/licenses/LICENSE
quantum_sync/__init__.py
quantum_sync/equalizer.py
quantum_sync/projection.py
quantum_sync/pyramid.py
quantum_sync/signature.py
urabi/__init__.py
urabi/blockchain/__init__.py
urabi/crypto/__init__.py
urabi/crypto/gost_crypto.py
urabi/crypto/gost_encryption.py
urabi/crypto/gost_hash.py
urabi/crypto/gost_signature.py
urabi/crypto/quantum_crypto.py
urabi/sip/__init__.py
libequalizer-1.0.0.dist-info/METADATA
libequalizer-1.0.0.dist-info/WHEEL
libequalizer-1.0.0.dist-info/entry_points.txt
libequalizer-1.0.0.dist-info/top_level.txt
libequalizer-1.0.0.dist-info/RECORD
